mtki/__init__.py
mtki/_mtki.cpython-310-x86_64-linux-gnu.so
morphologicaltoolkitforimages-0.2.1.dist-info/METADATA
morphologicaltoolkitforimages-0.2.1.dist-info/WHEEL
morphologicaltoolkitforimages-0.2.1.dist-info/RECORD
morphologicaltoolkitforimages-0.2.1.dist-info/licenses/LICENSE
