Metadata-Version: 2.2
Name: MorphologicalToolkitForImages
Version: 0.2.1
Summary: Biblioteca para geração de árvores morfológicas, extração de atributos e aplicação de filtros em imagens.
Keywords: morfologia,imagens,PyTorch,C++,Pybind11
Author-Email: Lucas de Paula Oliveira Santos <lkslukas23@gmail.com>
License: MIT
Requires-Python: >=3.9
Requires-Dist: opencv-python>=4.7
Requires-Dist: matplotlib>=3.7
Requires-Dist: torch>=2.5; sys_platform != "darwin" or platform_machine == "arm64"
Requires-Dist: numpy>=1.26; sys_platform != "darwin" or platform_machine == "arm64"
Requires-Dist: torch>=2.0; sys_platform == "darwin" and platform_machine == "x86_64"
Requires-Dist: numpy<=1.26; sys_platform == "darwin" and platform_machine == "x86_64"
